LICENSE
README.md
pyproject.toml
setup.py
src/xbern_confidence_intervals/__init__.py
src/xbern_confidence_intervals/asymptotic.py
src/xbern_confidence_intervals/asymptotic_vectorized.py
src/xbern_confidence_intervals/nonasymptotic.py
src/xbern_confidence_intervals.egg-info/PKG-INFO
src/xbern_confidence_intervals.egg-info/SOURCES.txt
src/xbern_confidence_intervals.egg-info/dependency_links.txt
src/xbern_confidence_intervals.egg-info/requires.txt
src/xbern_confidence_intervals.egg-info/top_level.txt